pdm_download-0.2.0.dist-info/METADATA
pdm_download-0.2.0.dist-info/WHEEL
pdm_download-0.2.0.dist-info/entry_points.txt
pdm_download-0.2.0.dist-info/licenses/LICENSE
pdm_download/__init__.py
pdm_download/command.py
pdm_download-0.2.0.dist-info/RECORD
