Metadata-Version: 2.1
Name: pdm-download
Version: 0.2.0
Summary: A PDM plugin to download all packages in a lockfile for offline use.
Author-Email: Frost Ming <me@frostming.com>
License: MIT
Classifier: Programming Language :: Python :: 3 :: Only
Classifier: Programming Language :: Python :: 3.8
Classifier: Programming Language :: Python :: 3.9
Classifier: Programming Language :: Python :: 3.10
Classifier: Programming Language :: Python :: 3.11
Classifier: Programming Language :: Python :: 3.12
Project-URL: Repository, https://github.com/pdm-project/pdm-download
Requires-Python: >=3.8
Requires-Dist: rich>=13
